Metadata-Version: 1.1
Name: aTXT
Version: 1.0.5.7
Summary: data mining tool for extract text for files
Home-page: https://github.com/d555/python-atxt
Author: Jonathan Steven Prieto C.
Author-email: prieto.jona@gmail.com
License: BSD
Keywords: text,extraction,mining,tool,data,pdf2txt,csv2txt,text,txt,doc,docx,pdf,csv,png,jpg,doc2txt,docx2txt,convert
Platform: UNKNOWN
Classifier: Development Status :: 5 - Production/Stable
Classifier: Intended Audience :: Developers
Classifier: License :: OSI Approved :: BSD License
Classifier: Operating System :: Unix
Classifier: Operating System :: POSIX
Classifier: Operating System :: Microsoft :: Windows
Classifier: Programming Language :: Python :: 2.7
Classifier: Programming Language :: Python :: 3.4
Classifier: Topic :: Utilities
